setup.py
weblate_tools/__init__.py
weblate_tools/divider.py
weblate_tools/poster.py
weblate_tools/reader.py
weblate_tools/writer.py
weblate_tools.egg-info/PKG-INFO
weblate_tools.egg-info/SOURCES.txt
weblate_tools.egg-info/dependency_links.txt
weblate_tools.egg-info/pbr.json
weblate_tools.egg-info/requires.txt
weblate_tools.egg-info/top_level.txt