Metadata-Version: 1.0
Name: weblate-tools
Version: 0.1.0
Summary: weblate文本处理工具
Home-page: https://github.com/zhufree/WeblateTools
Author: zhufree
Author-email: zhufree2013@gmail.com
License: UNKNOWN
Keywords: weblate,translate
Platform: UNKNOWN
